{
    "000": {
        "coord": [
            0.08658284407020961,
            0.4255
        ],
        "angle": 64.6875,
        "candidate_coord": [
            [
                0.08658284407020961,
                0.4255
            ],
            [
                0.2305828440702096,
                0.4255
            ],
            [
                0.06258284407020959,
                0.4255
            ],
            [
                0.2225828440702096,
                0.4255
            ]
        ],
        "candidate_angle": [
            64.6875,
            64.6875,
            66.09375,
            64.6875
        ]
    },
    "001": {
        "coord": [
            0.10975593020172883,
            0.420989
        ],
        "angle": 45.0,
        "candidate_coord": [
            [
                0.10975593020172883,
                0.420989
            ],
            [
                0.021755930201728835,
                0.420989
            ],
            [
                0.03775593020172882,
                0.420989
            ],
            [
                0.18175593020172884,
                0.420989
            ]
        ],
        "candidate_angle": [
            45.0,
            45.0,
            45.0,
            46.40625
        ]
    },
    "002": {
        "coord": [
            0.2606696143706424,
            0.416478
        ],
        "angle": 43.59375,
        "candidate_coord": [
            [
                0.2606696143706424,
                0.416478
            ],
            [
                0.10066961437064242,
                0.416478
            ],
            [
                0.0446696143706424,
                0.416478
            ],
            [
                0.22866961437064243,
                0.416478
            ]
        ],
        "candidate_angle": [
            43.59375,
            40.78125,
            40.78125,
            42.1875
        ]
    },
    "003": {
        "coord": [
            0.13134288576034522,
            0.41196699999999997
        ],
        "angle": 42.1875,
        "candidate_coord": [
            [
                0.13134288576034522,
                0.41196699999999997
            ],
            [
                0.1473428857603452,
                0.41196699999999997
            ],
            [
                0.09934288576034522,
                0.41196699999999997
            ],
            [
                0.17134288576034523,
                0.41196699999999997
            ]
        ],
        "candidate_angle": [
            42.1875,
            40.78125,
            40.78125,
            40.78125
        ]
    },
    "004": {
        "coord": [
            0.16179235335667502,
            0.407456
        ],
        "angle": 59.0625,
        "candidate_coord": [
            [
                0.16179235335667502,
                0.407456
            ],
            [
                0.009792353356674999,
                0.407456
            ],
            [
                0.10579235335667503,
                0.407456
            ],
            [
                0.18579235335667502,
                0.407456
            ]
        ],
        "candidate_angle": [
            59.0625,
            57.65625,
            59.0625,
            59.0625
        ]
    },
    "005": {
        "coord": [
            0.14403264511705463,
            0.402945
        ],
        "angle": 59.0625,
        "candidate_coord": [
            [
                0.14403264511705463,
                0.402945
            ],
            [
                0.18403264511705464,
                0.402945
            ],
            [
                0.13603264511705462,
                0.402945
            ],
            [
                0.08003264511705463,
                0.402945
            ]
        ],
        "candidate_angle": [
            59.0625,
            59.0625,
            57.65625,
            59.0625
        ]
    },
    "006": {
        "coord": [
            0.1420767247637593,
            0.398434
        ],
        "angle": 59.0625,
        "candidate_coord": [
            [
                0.1420767247637593,
                0.398434
            ],
            [
                0.10207672476375929,
                0.398434
            ],
            [
                0.1340767247637593,
                0.398434
            ],
            [
                0.2140767247637593,
                0.398434
            ]
        ],
        "candidate_angle": [
            59.0625,
            59.0625,
            59.0625,
            59.0625
        ]
    },
    "007": {
        "coord": [
            0.22793614609363422,
            0.39392299999999997
        ],
        "angle": 59.0625,
        "candidate_coord": [
            [
                0.22793614609363422,
                0.39392299999999997
            ],
            [
                0.23593614609363422,
                0.39392299999999997
            ],
            [
                0.24393614609363423,
                0.39392299999999997
            ],
            [
                0.30793614609363423,
                0.39392299999999997
            ]
        ],
        "candidate_angle": [
            59.0625,
            59.0625,
            59.0625,
            59.0625
        ]
    },
    "008": {
        "coord": [
            0.2176212592538969,
            0.389412
        ],
        "angle": 56.25,
        "candidate_coord": [
            [
                0.2176212592538969,
                0.389412
            ],
            [
                0.14562125925389688,
                0.389412
            ],
            [
                0.12162125925389689,
                0.389412
            ],
            [
                0.15362125925389689,
                0.389412
            ]
        ],
        "candidate_angle": [
            56.25,
            56.25,
            56.25,
            56.25
        ]
    },
    "009": {
        "coord": [
            0.19914137964074796,
            0.384901
        ],
        "angle": 56.25,
        "candidate_coord": [
            [
                0.19914137964074796,
                0.384901
            ],
            [
                0.22314137964074796,
                0.384901
            ],
            [
                0.30314137964074794,
                0.384901
            ],
            [
                0.27114137964074797,
                0.384901
            ]
        ],
        "candidate_angle": [
            56.25,
            56.25,
            57.65625,
            56.25
        ]
    },
    "010": {
        "coord": [
            0.22850492738940034,
            0.38039
        ],
        "angle": 57.65625,
        "candidate_coord": [
            [
                0.22850492738940034,
                0.38039
            ],
            [
                0.30850492738940033,
                0.38039
            ],
            [
                0.21250492738940036,
                0.38039
            ],
            [
                0.20450492738940035,
                0.38039
            ]
        ],
        "candidate_angle": [
            57.65625,
            57.65625,
            56.25,
            56.25
        ]
    },
    "011": {
        "coord": [
            0.14571954348961486,
            0.37587899999999996
        ],
        "angle": 54.84375,
        "candidate_coord": [
            [
                0.14571954348961486,
                0.37587899999999996
            ],
            [
                0.15371954348961486,
                0.37587899999999996
            ],
            [
                0.22571954348961484,
                0.37587899999999996
            ],
            [
                0.28171954348961487,
                0.37587899999999996
            ]
        ],
        "candidate_angle": [
            54.84375,
            54.84375,
            56.25,
            56.25
        ]
    },
    "012": {
        "coord": [
            0.2307921871489835,
            0.371368
        ],
        "angle": 57.65625,
        "candidate_coord": [
            [
                0.2307921871489835,
                0.371368
            ],
            [
                0.1907921871489835,
                0.371368
            ],
            [
                0.2547921871489835,
                0.371368
            ],
            [
                0.3267921871489835,
                0.371368
            ]
        ],
        "candidate_angle": [
            57.65625,
            56.25,
            56.25,
            57.65625
        ]
    },
    "013": {
        "coord": [
            0.32372921798249854,
            0.366857
        ],
        "angle": 64.6875,
        "candidate_coord": [
            [
                0.32372921798249854,
                0.366857
            ],
            [
                0.33972921798249855,
                0.366857
            ],
            [
                0.22772921798249857,
                0.366857
            ],
            [
                0.25972921798249854,
                0.366857
            ]
        ],
        "candidate_angle": [
            64.6875,
            63.28125,
            63.28125,
            63.28125
        ]
    },
    "014": {
        "coord": [
            0.18453646582618796,
            0.362346
        ],
        "angle": 49.21875,
        "candidate_coord": [
            [
                0.18453646582618796,
                0.362346
            ],
            [
                0.19253646582618797,
                0.362346
            ],
            [
                0.27253646582618796,
                0.362346
            ],
            [
                0.24853646582618796,
                0.362346
            ]
        ],
        "candidate_angle": [
            49.21875,
            49.21875,
            50.625,
            49.21875
        ]
    },
    "015": {
        "coord": [
            0.21321929038213222,
            0.357835
        ],
        "angle": 49.21875,
        "candidate_coord": [
            [
                0.21321929038213222,
                0.357835
            ],
            [
                0.18921929038213223,
                0.357835
            ],
            [
                0.22921929038213223,
                0.357835
            ],
            [
                0.3332192903821322,
                0.357835
            ]
        ],
        "candidate_angle": [
            49.21875,
            49.21875,
            49.21875,
            50.625
        ]
    },
    "016": {
        "coord": [
            0.21778263245105745,
            0.35332399999999997
        ],
        "angle": 47.8125,
        "candidate_coord": [
            [
                0.21778263245105745,
                0.35332399999999997
            ],
            [
                0.22578263245105745,
                0.35332399999999997
            ],
            [
                0.3137826324510575,
                0.35332399999999997
            ],
            [
                0.24978263245105745,
                0.35332399999999997
            ]
        ],
        "candidate_angle": [
            47.8125,
            47.8125,
            49.21875,
            49.21875
        ]
    },
    "017": {
        "coord": [
            0.27023105816079096,
            0.348813
        ],
        "angle": 47.8125,
        "candidate_coord": [
            [
                0.27023105816079096,
                0.348813
            ],
            [
                0.286231058160791,
                0.348813
            ],
            [
                0.206231058160791,
                0.348813
            ],
            [
                0.25423105816079095,
                0.348813
            ]
        ],
        "candidate_angle": [
            47.8125,
            47.8125,
            47.8125,
            47.8125
        ]
    },
    "018": {
        "coord": [
            0.29056879732817603,
            0.344302
        ],
        "angle": 47.8125,
        "candidate_coord": [
            [
                0.29056879732817603,
                0.344302
            ],
            [
                0.30656879732817605,
                0.344302
            ],
            [
                0.346568797328176,
                0.344302
            ],
            [
                0.29856879732817604,
                0.344302
            ]
        ],
        "candidate_angle": [
            47.8125,
            47.8125,
            47.8125,
            47.8125
        ]
    },
    "019": {
        "coord": [
            0.26279977687970313,
            0.33979099999999995
        ],
        "angle": 45.0,
        "candidate_coord": [
            [
                0.26279977687970313,
                0.33979099999999995
            ],
            [
                0.3187997768797032,
                0.33979099999999995
            ],
            [
                0.23079977687970316,
                0.33979099999999995
            ],
            [
                0.27079977687970314,
                0.33979099999999995
            ]
        ],
        "candidate_angle": [
            45.0,
            46.40625,
            45.0,
            45.0
        ]
    },
    "020": {
        "coord": [
            0.3469276500882618,
            0.33527999999999997
        ],
        "angle": 43.59375,
        "candidate_coord": [
            [
                0.3469276500882618,
                0.33527999999999997
            ],
            [
                0.25092765008826184,
                0.33527999999999997
            ],
            [
                0.23492765008826183,
                0.33527999999999997
            ],
            [
                0.22692765008826182,
                0.33527999999999997
            ]
        ],
        "candidate_angle": [
            43.59375,
            43.59375,
            43.59375,
            43.59375
        ]
    },
    "021": {
        "coord": [
            0.32695582224976855,
            0.330769
        ],
        "angle": 43.59375,
        "candidate_coord": [
            [
                0.32695582224976855,
                0.330769
            ],
            [
                0.23895582224976852,
                0.330769
            ],
            [
                0.26295582224976854,
                0.330769
            ],
            [
                0.27095582224976855,
                0.330769
            ]
        ],
        "candidate_angle": [
            43.59375,
            42.1875,
            43.59375,
            43.59375
        ]
    },
    "022": {
        "coord": [
            0.2748874733162868,
            0.326258
        ],
        "angle": 42.1875,
        "candidate_coord": [
            [
                0.2748874733162868,
                0.326258
            ],
            [
                0.32288747331628687,
                0.326258
            ],
            [
                0.26688747331628687,
                0.326258
            ],
            [
                0.25888747331628686,
                0.326258
            ]
        ],
        "candidate_angle": [
            42.1875,
            43.59375,
            43.59375,
            42.1875
        ]
    },
    "023": {
        "coord": [
            0.3027255779158221,
            0.321747
        ],
        "angle": 42.1875,
        "candidate_coord": [
            [
                0.3027255779158221,
                0.321747
            ],
            [
                0.2547255779158221,
                0.321747
            ],
            [
                0.26272557791582213,
                0.321747
            ],
            [
                0.24672557791582211,
                0.321747
            ]
        ],
        "candidate_angle": [
            42.1875,
            42.1875,
            42.1875,
            42.1875
        ]
    },
    "024": {
        "coord": [
            0.2824729231188131,
            0.31723599999999996
        ],
        "angle": 42.1875,
        "candidate_coord": [
            [
                0.2824729231188131,
                0.31723599999999996
            ],
            [
                0.2584729231188131,
                0.31723599999999996
            ],
            [
                0.2984729231188131,
                0.31723599999999996
            ],
            [
                0.3064729231188131,
                0.31723599999999996
            ]
        ],
        "candidate_angle": [
            42.1875,
            42.1875,
            40.78125,
            40.78125
        ]
    },
    "025": {
        "coord": [
            0.35013212425407886,
            0.312725
        ],
        "angle": 42.1875,
        "candidate_coord": [
            [
                0.35013212425407886,
                0.312725
            ],
            [
                0.34213212425407885,
                0.312725
            ],
            [
                0.27013212425407884,
                0.312725
            ],
            [
                0.32613212425407884,
                0.312725
            ]
        ],
        "candidate_angle": [
            42.1875,
            42.1875,
            40.78125,
            40.78125
        ]
    },
    "026": {
        "coord": [
            0.27370563902997375,
            0.308214
        ],
        "angle": 40.78125,
        "candidate_coord": [
            [
                0.27370563902997375,
                0.308214
            ],
            [
                0.32170563902997373,
                0.308214
            ],
            [
                0.28170563902997375,
                0.308214
            ],
            [
                0.38570563902997373,
                0.308214
            ]
        ],
        "candidate_angle": [
            40.78125,
            40.78125,
            42.1875,
            40.78125
        ]
    },
    "027": {
        "coord": [
            0.33319578017773555,
            0.303703
        ],
        "angle": 39.375,
        "candidate_coord": [
            [
                0.33319578017773555,
                0.303703
            ],
            [
                0.39719578017773555,
                0.303703
            ],
            [
                0.26919578017773554,
                0.303703
            ],
            [
                0.32519578017773554,
                0.303703
            ]
        ],
        "candidate_angle": [
            39.375,
            40.78125,
            39.375,
            39.375
        ]
    },
    "028": {
        "coord": [
            0.32860472680186886,
            0.299192
        ],
        "angle": 37.96875,
        "candidate_coord": [
            [
                0.32860472680186886,
                0.299192
            ],
            [
                0.3126047268018689,
                0.299192
            ],
            [
                0.3526047268018689,
                0.299192
            ],
            [
                0.32060472680186886,
                0.299192
            ]
        ],
        "candidate_angle": [
            37.96875,
            37.96875,
            37.96875,
            37.96875
        ]
    },
    "029": {
        "coord": [
            0.3479345345956446,
            0.29468099999999997
        ],
        "angle": 37.96875,
        "candidate_coord": [
            [
                0.3479345345956446,
                0.29468099999999997
            ],
            [
                0.3559345345956446,
                0.29468099999999997
            ],
            [
                0.4039345345956446,
                0.29468099999999997
            ],
            [
                0.3319345345956446,
                0.29468099999999997
            ]
        ],
        "candidate_angle": [
            37.96875,
            37.96875,
            37.96875,
            37.96875
        ]
    },
    "030": {
        "coord": [
            0.32718714505740476,
            0.29017
        ],
        "angle": 37.96875,
        "candidate_coord": [
            [
                0.32718714505740476,
                0.29017
            ],
            [
                0.33518714505740477,
                0.29017
            ],
            [
                0.2871871450574048,
                0.29017
            ],
            [
                0.3671871450574048,
                0.29017
            ]
        ],
        "candidate_angle": [
            37.96875,
            37.96875,
            36.5625,
            37.96875
        ]
    },
    "031": {
        "coord": [
            0.3063643938245617,
            0.285659
        ],
        "angle": 36.5625,
        "candidate_coord": [
            [
                0.3063643938245617,
                0.285659
            ],
            [
                0.34636439382456174,
                0.285659
            ],
            [
                0.3783643938245618,
                0.285659
            ],
            [
                0.36236439382456176,
                0.285659
            ]
        ],
        "candidate_angle": [
            36.5625,
            36.5625,
            36.5625,
            36.5625
        ]
    },
    "032": {
        "coord": [
            0.3734680182263195,
            0.28114799999999995
        ],
        "angle": 35.15625,
        "candidate_coord": [
            [
                0.3734680182263195,
                0.28114799999999995
            ],
            [
                0.32546801822631943,
                0.28114799999999995
            ],
            [
                0.3814680182263195,
                0.28114799999999995
            ],
            [
                0.29346801822631946,
                0.28114799999999995
            ]
        ],
        "candidate_angle": [
            35.15625,
            33.75,
            35.15625,
            33.75
        ]
    },
    "033": {
        "coord": [
            0.3284996641427217,
            0.276637
        ],
        "angle": 33.75,
        "candidate_coord": [
            [
                0.3284996641427217,
                0.276637
            ],
            [
                0.3044996641427217,
                0.276637
            ],
            [
                0.4164996641427217,
                0.276637
            ],
            [
                0.4004996641427217,
                0.276637
            ]
        ],
        "candidate_angle": [
            33.75,
            33.75,
            35.15625,
            35.15625
        ]
    },
    "034": {
        "coord": [
            0.371460892246226,
            0.272126
        ],
        "angle": 33.75,
        "candidate_coord": [
            [
                0.371460892246226,
                0.272126
            ],
            [
                0.38746089224622604,
                0.272126
            ],
            [
                0.37946089224622603,
                0.272126
            ],
            [
                0.315460892246226,
                0.272126
            ]
        ],
        "candidate_angle": [
            33.75,
            33.75,
            33.75,
            33.75
        ]
    },
    "035": {
        "coord": [
            0.38235318369227433,
            0.267615
        ],
        "angle": 33.75,
        "candidate_coord": [
            [
                0.38235318369227433,
                0.267615
            ],
            [
                0.3743531836922743,
                0.267615
            ],
            [
                0.4223531836922743,
                0.267615
            ],
            [
                0.39035318369227434,
                0.267615
            ]
        ],
        "candidate_angle": [
            33.75,
            33.75,
            33.75,
            33.75
        ]
    },
    "036": {
        "coord": [
            0.3531779453170167,
            0.263104
        ],
        "angle": 32.34375,
        "candidate_coord": [
            [
                0.3531779453170167,
                0.263104
            ],
            [
                0.3611779453170167,
                0.263104
            ],
            [
                0.4091779453170167,
                0.263104
            ],
            [
                0.3211779453170167,
                0.263104
            ]
        ],
        "candidate_angle": [
            32.34375,
            32.34375,
            32.34375,
            32.34375
        ]
    },
    "037": {
        "coord": [
            0.3719365143931983,
            0.25859299999999996
        ],
        "angle": 32.34375,
        "candidate_coord": [
            [
                0.3719365143931983,
                0.25859299999999996
            ],
            [
                0.3479365143931983,
                0.25859299999999996
            ],
            [
                0.3799365143931983,
                0.25859299999999996
            ],
            [
                0.3559365143931983,
                0.25859299999999996
            ]
        ],
        "candidate_angle": [
            32.34375,
            32.34375,
            30.9375,
            32.34375
        ]
    },
    "038": {
        "coord": [
            0.3426301629890781,
            0.254082
        ],
        "angle": 30.9375,
        "candidate_coord": [
            [
                0.3426301629890781,
                0.254082
            ],
            [
                0.3586301629890781,
                0.254082
            ],
            [
                0.36663016298907813,
                0.254082
            ],
            [
                0.3506301629890781,
                0.254082
            ]
        ],
        "candidate_angle": [
            30.9375,
            30.9375,
            32.34375,
            30.9375
        ]
    },
    "039": {
        "coord": [
            0.43326010196993675,
            0.249571
        ],
        "angle": 30.9375,
        "candidate_coord": [
            [
                0.43326010196993675,
                0.249571
            ],
            [
                0.42526010196993674,
                0.249571
            ],
            [
                0.34526010196993673,
                0.249571
            ],
            [
                0.36926010196993675,
                0.249571
            ]
        ],
        "candidate_angle": [
            30.9375,
            30.9375,
            30.9375,
            30.9375
        ]
    },
    "040": {
        "coord": [
            0.33982748467713697,
            0.24505999999999997
        ],
        "angle": 30.9375,
        "candidate_coord": [
            [
                0.33982748467713697,
                0.24505999999999997
            ],
            [
                0.37182748467713694,
                0.24505999999999997
            ],
            [
                0.38782748467713696,
                0.24505999999999997
            ],
            [
                0.347827484677137,
                0.24505999999999997
            ]
        ],
        "candidate_angle": [
            30.9375,
            30.9375,
            30.9375,
            29.53125
        ]
    },
    "041": {
        "coord": [
            0.39033341031570934,
            0.24054899999999999
        ],
        "angle": 29.53125,
        "candidate_coord": [
            [
                0.39033341031570934,
                0.24054899999999999
            ],
            [
                0.4143334103157093,
                0.24054899999999999
            ],
            [
                0.3583334103157093,
                0.24054899999999999
            ],
            [
                0.3423334103157093,
                0.24054899999999999
            ]
        ],
        "candidate_angle": [
            29.53125,
            30.9375,
            29.53125,
            30.9375
        ]
    },
    "042": {
        "coord": [
            0.40077892707796275,
            0.23603799999999997
        ],
        "angle": 30.9375,
        "candidate_coord": [
            [
                0.40077892707796275,
                0.23603799999999997
            ],
            [
                0.4167789270779627,
                0.23603799999999997
            ],
            [
                0.35277892707796277,
                0.23603799999999997
            ],
            [
                0.39277892707796275,
                0.23603799999999997
            ]
        ],
        "candidate_angle": [
            30.9375,
            29.53125,
            29.53125,
            30.9375
        ]
    },
    "043": {
        "coord": [
            0.4431650350275843,
            0.23152699999999998
        ],
        "angle": 28.125,
        "candidate_coord": [
            [
                0.4431650350275843,
                0.23152699999999998
            ],
            [
                0.3791650350275843,
                0.23152699999999998
            ],
            [
                0.4111650350275843,
                0.23152699999999998
            ],
            [
                0.40316503502758433,
                0.23152699999999998
            ]
        ],
        "candidate_angle": [
            28.125,
            28.125,
            28.125,
            28.125
        ]
    },
    "044": {
        "coord": [
            0.37349268876604474,
            0.22701599999999997
        ],
        "angle": 28.125,
        "candidate_coord": [
            [
                0.37349268876604474,
                0.22701599999999997
            ],
            [
                0.34149268876604477,
                0.22701599999999997
            ],
            [
                0.44549268876604475,
                0.22701599999999997
            ],
            [
                0.4134926887660447,
                0.22701599999999997
            ]
        ],
        "candidate_angle": [
            28.125,
            28.125,
            28.125,
            28.125
        ]
    },
    "045": {
        "coord": [
            0.4397627999007957,
            0.22250499999999998
        ],
        "angle": 28.125,
        "candidate_coord": [
            [
                0.4397627999007957,
                0.22250499999999998
            ],
            [
                0.4317627999007957,
                0.22250499999999998
            ],
            [
                0.4477627999007957,
                0.22250499999999998
            ],
            [
                0.4157627999007957,
                0.22250499999999998
            ]
        ],
        "candidate_angle": [
            28.125,
            28.125,
            28.125,
            28.125
        ]
    },
    "046": {
        "coord": [
            0.35397623933270084,
            0.21799399999999997
        ],
        "angle": 26.71875,
        "candidate_coord": [
            [
                0.35397623933270084,
                0.21799399999999997
            ],
            [
                0.36197623933270084,
                0.21799399999999997
            ],
            [
                0.3779762393327008,
                0.21799399999999997
            ],
            [
                0.4019762393327008,
                0.21799399999999997
            ]
        ],
        "candidate_angle": [
            26.71875,
            26.71875,
            26.71875,
            26.71875
        ]
    },
    "047": {
        "coord": [
            0.4201338393783416,
            0.21348299999999998
        ],
        "angle": 26.71875,
        "candidate_coord": [
            [
                0.4201338393783416,
                0.21348299999999998
            ],
            [
                0.3801338393783416,
                0.21348299999999998
            ],
            [
                0.36413383937834165,
                0.21348299999999998
            ],
            [
                0.35613383937834164,
                0.21348299999999998
            ]
        ],
        "candidate_angle": [
            26.71875,
            26.71875,
            26.71875,
            26.71875
        ]
    },
    "048": {
        "coord": [
            0.38223639574124835,
            0.208972
        ],
        "angle": 25.3125,
        "candidate_coord": [
            [
                0.38223639574124835,
                0.208972
            ],
            [
                0.4222363957412484,
                0.208972
            ],
            [
                0.39023639574124835,
                0.208972
            ],
            [
                0.40623639574124837,
                0.208972
            ]
        ],
        "candidate_angle": [
            25.3125,
            26.71875,
            25.3125,
            26.71875
        ]
    },
    "049": {
        "coord": [
            0.3682846693446976,
            0.20446099999999998
        ],
        "angle": 25.3125,
        "candidate_coord": [
            [
                0.3682846693446976,
                0.20446099999999998
            ],
            [
                0.3602846693446976,
                0.20446099999999998
            ],
            [
                0.4082846693446976,
                0.20446099999999998
            ],
            [
                0.4482846693446976,
                0.20446099999999998
            ]
        ],
        "candidate_angle": [
            25.3125,
            25.3125,
            25.3125,
            26.71875
        ]
    }
}